Finger_balabolka-1.0.25.dist-info/DESCRIPTION.rst
Finger_balabolka-1.0.25.dist-info/METADATA
Finger_balabolka-1.0.25.dist-info/RECORD
Finger_balabolka-1.0.25.dist-info/WHEEL
Finger_balabolka-1.0.25.dist-info/entry_points.txt
Finger_balabolka-1.0.25.dist-info/metadata.json
Finger_balabolka-1.0.25.dist-info/top_level.txt
fb_client/__init__.py
fb_client/main.py
fb_client/test_client.py
fb_client/accounts/__init__.py
fb_client/accounts/account.py
fb_client/accounts/db/__init__.py
fb_client/accounts/db/models.py
fb_client/accounts/db/settings.py
fb_client/core/__init__.py
fb_client/core/client.py
fb_client/core/handlers.py
fb_client/protocol/__init__.py
fb_client/protocol/jim.py
fb_client/ui/__init__.py
fb_client/ui/acc_settings.py
fb_client/ui/dialogs.py
fb_client/ui/gui_class.py
fb_client/ui/img/add_icon.png
fb_client/ui/img/finger-man.png
fb_client/ui/img/icon.png
fb_client/ui/ui_files/__init__.py
fb_client/ui/ui_files/about_ui.py
fb_client/ui/ui_files/acc_set_ui.py
fb_client/ui/ui_files/client_ui.py
fb_client/ui/ui_files/enter_ui.py
fb_client/ui/ui_files/help_ui.py
fb_client/utils/__init__.py
fb_client/utils/decorators.py
fb_client/utils/log_config.py
fb_client/utils/utils.py
